kapt_catalog/__init__.py
kapt_catalog/admin/__init__.py
kapt_catalog/admin/activities/__init__.py
kapt_catalog/admin/activities/accommodation.py
kapt_catalog/admin/activities/activity.py
kapt_catalog/admin/activities/base.py
kapt_catalog/admin/activities/event.py
kapt_catalog/admin/activities/leisure.py
kapt_catalog/admin/activities/meal.py
kapt_catalog/admin/activities/poi.py
kapt_catalog/admin/base.py
kapt_catalog/apps.py
kapt_catalog/cmsplugin_list/README.md
kapt_catalog/cmsplugin_list/__init__.py
kapt_catalog/cmsplugin_list/cms_plugins.py
kapt_catalog/cmsplugin_list/cmspluginlist_filters.py
kapt_catalog/cmsplugin_list/conf/__init__.py
kapt_catalog/cmsplugin_list/conf/settings.py
kapt_catalog/cmsplugin_list/fields.py
kapt_catalog/cmsplugin_list/fields_select2.py
kapt_catalog/cmsplugin_list/fields_select2_legacy.py
kapt_catalog/cmsplugin_list/forms.py
kapt_catalog/cmsplugin_list/locale/es/LC_MESSAGES/django.mo
kapt_catalog/cmsplugin_list/locale/es/LC_MESSAGES/django.po
kapt_catalog/cmsplugin_list/locale/fr/LC_MESSAGES/django.mo
kapt_catalog/cmsplugin_list/locale/fr/LC_MESSAGES/django.po
kapt_catalog/cmsplugin_list/management/__init__.py
kapt_catalog/cmsplugin_list/management/commands/__init__.py
kapt_catalog/cmsplugin_list/management/commands/apply_default_context_processor.py
kapt_catalog/cmsplugin_list/management/commands/empty_results_per_page.py
kapt_catalog/cmsplugin_list/management/commands/reinit_plugins_config.py
kapt_catalog/cmsplugin_list/migrations/0001_initial.py
kapt_catalog/cmsplugin_list/migrations/__init__.py
kapt_catalog/cmsplugin_list/models.py
kapt_catalog/conf/__init__.py
kapt_catalog/conf/settings.py
kapt_catalog/constants.py
kapt_catalog/core/__init__.py
kapt_catalog/core/db/__init__.py
kapt_catalog/core/db/choices.py
kapt_catalog/fixtures/characteristic.json
kapt_catalog/fixtures/spokenlanguage.json
kapt_catalog/forms/__init__.py
kapt_catalog/forms/activities/__init__.py
kapt_catalog/forms/activities/accommodation.py
kapt_catalog-6.2.11.dist-info/LICENSE.txt
kapt_catalog-6.2.11.dist-info/METADATA
kapt_catalog-6.2.11.dist-info/WHEEL
kapt_catalog-6.2.11.dist-info/RECORD
