Metadata-Version: 2.1
Name: kapt-catalog
Version: 6.2.11
Summary: Kapt catalog
License: LICENSE.txt
Author: Kapt dev team
Author-email: dev@kapt.mobi
Requires-Python: >=3.8.1,<4.0.0
Classifier: License :: Other/Proprietary License
Classifier: Programming Language :: Python :: 3
Classifier: Programming Language :: Python :: 3.9
Classifier: Programming Language :: Python :: 3.10
Classifier: Programming Language :: Python :: 3.11
Classifier: Programming Language :: Python :: 3.12
Provides-Extra: cms
Requires-Dist: Babel
Requires-Dist: Django (>=1.11)
Requires-Dist: django-extra-views
Requires-Dist: django-model-utils
Requires-Dist: django-modeltranslation
Requires-Dist: django-mptt
Requires-Dist: django-multiselectfield
Requires-Dist: django-parler
Requires-Dist: django-taggit
Requires-Dist: django_mptt_admin
Requires-Dist: django_polymorphic
Requires-Dist: kapt-contact
Requires-Dist: kapt-gallery
Requires-Dist: kapt-geo
Requires-Dist: kapt-meta
Requires-Dist: kapt-utils
Requires-Dist: kapt-validity
Requires-Dist: python-slugify
Requires-Dist: xlrd ; extra == "cms"
